[
  {
    "date": "2026-07-19",
    "description": "Rock & Roll Summer Vibes! ",
    "location": "Hatsiekedeeplein' / Markt  · OOSTERHOUT (NB) -    15:00",
    "flyer": "assets/shows/rock-roll-summer-vibes-2026-07-19-mr5yhuwc.jpg",
    "thumb": "assets/shows/rock-roll-summer-vibes-2026-07-19-mr5yhuwc-thumb.jpg",
    "ticket": ""
  },
  {
    "date": "2026-07-26",
    "description": "ROCK AND ROLL SUMMER DANCE PARTY! OUTDOORS ",
    "location": "'De Boemel' · TILBURG - 15:00  - Burgemeester Brokxlaan 8-76",
    "flyer": "assets/shows/2026-07-26-boemel-tilburg.jpg",
    "thumb": "assets/shows/2026-07-26-boemel-tilburg-thumb.jpg",
    "ticket": ""
  },
  {
    "date": "2026-08-01",
    "description": "The Explosion Rockets @ Jailhouse Rock Festival ",
    "location": "'Sauerpark' · ROSPORT (Luxemburg) - vanaf 14:30",
    "flyer": "assets/shows/the-explosion-rockets-jailhouse-rock-fes-2026-08-01-mreucje5.jpg",
    "thumb": "assets/shows/the-explosion-rockets-jailhouse-rock-fes-2026-08-01-mreucje5-thumb.jpg",
    "ticket": ""
  },
  {
    "date": "2026-08-08",
    "description": "The Explosion Rockets at Summershelter Festival - Open Air Festival bei Magdeburg ",
    "location": "Biederitz  · DUITSLAND - 16:30- 18:00 - Parkweg 1A ",
    "flyer": "assets/shows/2026-08-08-magdeburg.jpg",
    "thumb": "assets/shows/2026-08-08-magdeburg-thumb.jpg",
    "ticket": ""
  },
  {
    "date": "2026-08-15",
    "description": "Bog & Roll Festival ",
    "location": "Centrum · VEENDAM - 12:00 tot 18:00",
    "flyer": "assets/shows/bog-roll-festival-2026-08-15-mr5yitn5.jpg",
    "thumb": "assets/shows/bog-roll-festival-2026-08-15-mr5yitn5-thumb.jpg",
    "ticket": ""
  },
  {
    "date": "2026-08-30",
    "description": "The Explosion Rockets at Plein Musique ",
    "location": "Burchtplein · WASSENAAR - 15:30",
    "flyer": "assets/shows/the-explosion-rockets-at-plein-musique-1-2026-08-30-mr5zg37o.jpg",
    "thumb": "assets/shows/the-explosion-rockets-at-plein-musique-1-2026-08-30-mr5zg37o-thumb.jpg",
    "ticket": ""
  },
  {
    "date": "2026-09-06",
    "description": "Akercity Rock & Roll Weekend — 5th Anniversary",
    "location": "Wilhelminaplein · AKERSLOOT (NH)",
    "flyer": "assets/shows/akercity-rock-roll-weekend-5th-anniversa-2026-09-06-mr8rptqb.jpg",
    "thumb": "assets/shows/akercity-rock-roll-weekend-5th-anniversa-2026-09-06-mr8rptqb-thumb.jpg",
    "ticket": ""
  },
  {
    "date": "2026-09-26",
    "description": "'Blue Suede Shoes!' Dance Party ",
    "location": "'Zaal Hercules' · DIESSEN - 20:30 - Rijtseweg 1 ",
    "flyer": "assets/shows/2026-09-26-diessen.jpg",
    "thumb": "assets/shows/2026-09-26-diessen-thumb.jpg",
    "ticket": "https://www.ticketkantoor.nl/shop/HerculesDiessen"
  },
  {
    "date": "2026-10-11",
    "description": "Elvis & the Legends of Rock and Roll · Elvis Dag ",
    "location": "'Het Wapen van Steenbergen' · STEENBERGEN - Kaaistraat 12 - 11:00 tot 20:00 ",
    "flyer": "assets/shows/2026-10-11-steenbergen.jpg",
    "thumb": "assets/shows/2026-10-11-steenbergen-thumb.jpg",
    "ticket": "https://weeztix.shop/qrvnww4b"
  },
  {
    "date": "2026-10-18",
    "description": "20 jaar Explosion Rockets in 'De Post' — jubileumconcert ",
    "location": "'De Post' · MIDWOUD (NH) - 15:00 - Tripkouw 28 ",
    "flyer": "assets/shows/2026-10-18-de-post-midwoud.jpg",
    "thumb": "assets/shows/2026-10-18-de-post-midwoud-thumb.jpg",
    "ticket": ""
  },
  {
    "date": "2026-10-24",
    "description": "Besloten evenement",
    "location": "",
    "flyer": "",
    "thumb": "",
    "ticket": ""
  },
  {
    "date": "2026-11-08",
    "description": "The Explosion Rockets @ 'De Club' Eindhoven ",
    "location": "'De Club' · EINDHOVEN - 14:00 -  Dommelstraat 7 ",
    "flyer": "assets/shows/the-explosion-rockets-de-club-eindhoven-2026-11-08-mr5yldt0.jpg",
    "thumb": "assets/shows/the-explosion-rockets-de-club-eindhoven-2026-11-08-mr5yldt0-thumb.jpg",
    "ticket": "https://shop.weeztix.com/052aec58-aa6a-11f0-a9cb-7e126431635e/tickets"
  },
  {
    "date": "2026-11-22",
    "description": "The Golden Hits of Rock and Roll ",
    "location": "'Babbelz' · OOSTERHOUT (NB) - 15:00 - Klappeijstraat 11",
    "flyer": "assets/shows/2026-11-22-babbelz-oosterhout.jpg",
    "thumb": "assets/shows/2026-11-22-babbelz-oosterhout-thumb.jpg",
    "ticket": "info@cafebabbelz.nl / 06 122 976 83"
  },
  {
    "date": "2026-11-29",
    "description": "ROCK, ROLL, SWING AND JIVE! DANCE PARTY ",
    "location": "'De Rijper Eilanden' · DE RIJP (NB) - 14:00 - Zuiddijk 2A ",
    "flyer": "assets/shows/rock-roll-swing-and-jive-dance-party-2026-11-29-mr91tthf.jpg",
    "thumb": "assets/shows/rock-roll-swing-and-jive-dance-party-2026-11-29-mr91tthf-thumb.jpg",
    "ticket": "https://www.ticketkantoor.nl/shop/DeRijp"
  },
  {
    "date": "2026-12-20",
    "description": "Rock And Roll Christmas Dance Party ",
    "location": "'Bet Kolen' - TILBURG  - 15:00 - Broekhovenseweg 111 ",
    "flyer": "",
    "thumb": "",
    "ticket": ""
  },
  {
    "date": "2027-01-03",
    "description": "Rock And Roll New Year's Party! ",
    "location": "'De Werf'- HAUWERT (NH) - Heemraad Witweg 2 - 15:00",
    "flyer": "",
    "thumb": "",
    "ticket": ""
  },
  {
    "date": "2027-01-24",
    "description": "'Shake, Rattle And Roll!' - 12,5 Explosion Rockets Jubileum JOOST ROEST ",
    "location": "'Zaal 't Plein' · UDENHOUT - Tongerloplein 1 - 14:30",
    "flyer": "assets/shows/shake-rattle-and-roll-12-5-explosion-roc-2027-01-24-mr8tpbyl.jpg",
    "thumb": "assets/shows/shake-rattle-and-roll-12-5-explosion-roc-2027-01-24-mr8tpbyl-thumb.jpg",
    "ticket": ""
  },
  {
    "date": "2027-02-13",
    "description": "Valentine's Rock And Roll DanceParty! ",
    "location": "'Zidewinde'- SPRANG-CAPELLE - Julianalaan 1 - 20:30",
    "flyer": "assets/shows/valentine-s-rock-and-roll-dance-party-2027-02-13-mr58qhyf.jpg",
    "thumb": "assets/shows/valentine-s-rock-and-roll-dance-party-2027-02-13-mr58qhyf-thumb.jpg",
    "ticket": "https://www.zidewinde.com/details-en-registratie/the-explosion-rockets-live-bij-zidewinde"
  },
  {
    "date": "2027-02-27",
    "description": "The Explosion Rockets ft. Pete Storm (Johnny Cash Tribute) ",
    "location": "'De Rots' · BOXTEL - Nieuwe Nieuwstraat 7 - 20:30",
    "flyer": "assets/shows/the-explosion-rockets-ft-pete-storm-john-2027-02-27-mr63f6mf.jpg",
    "thumb": "assets/shows/the-explosion-rockets-ft-pete-storm-john-2027-02-27-mr63f6mf-thumb.jpg",
    "ticket": "https://www.ticketkantoor.nl/shop/DeRots"
  },
  {
    "date": "2027-03-13",
    "description": "'Don't Knock The Rock' Festival (UITVERKOCHT! - SOLD OUT! )",
    "location": "Hemsby Beach Holiday Village - ENGELAND",
    "flyer": "assets/shows/don-t-knock-the-rock-festival-uitverkoch-2027-03-13-mr58arcf.jpg",
    "thumb": "assets/shows/don-t-knock-the-rock-festival-uitverkoch-2027-03-13-mr58arcf-thumb.jpg",
    "ticket": ""
  },
  {
    "date": "2027-04-18",
    "description": "The Explosion Rockets 2 — 'Het Witte Schaap' ",
    "location": "'Het Witte Schaap' · BREDA -  Wegedoornpage 2 - 14:30",
    "flyer": "",
    "thumb": "",
    "ticket": ""
  },
  {
    "date": "2027-05-08",
    "description": "ROCK AROUND THE CLOCK!",
    "location": "zaal 'STAM' -  WOGNUM -  Raadhuisstraat 3 - 17:30",
    "flyer": "",
    "thumb": "",
    "ticket": ""
  },
  {
    "date": "2027-08-08",
    "description": "Oldtimer Dag",
    "location": "Lido terrein /  WAALWIJK",
    "flyer": "assets/shows/oldtimer-dag-2027-08-08-mr7hrf0j.jpg",
    "thumb": "assets/shows/oldtimer-dag-2027-08-08-mr7hrf0j-thumb.jpg",
    "ticket": ""
  },
  {
    "date": "2027-08-14",
    "description": "ROCKIN' WOUW - 10th Anniversary",
    "location": "Markt, WOUW",
    "flyer": "assets/shows/rockin-wouw-10th-anniversary-2027-08-14-mr7ht8z8.jpg",
    "thumb": "assets/shows/rockin-wouw-10th-anniversary-2027-08-14-mr7ht8z8-thumb.jpg",
    "ticket": ""
  },
  {
    "date": "2027-08-29",
    "description": "The Explosion Rockets live at American Vintage Unlimited Outdoor! - Ericssonstraat 2",
    "location": "American Vintage Unlimited · RIJEN",
    "flyer": "",
    "thumb": "",
    "ticket": ""
  },
  {
    "date": "2027-09-04",
    "description": "The Explosion Rockets @ Bournemouth",
    "location": "Bournemouth · ENGELAND",
    "flyer": "",
    "thumb": "",
    "ticket": ""
  }
]
